Metadata-Version: 2.1
Name: spotify-cli-linux
Version: 2.1.0
Summary: a command line interface to Spotify on Linux
Home-page: https://github.com/pwittchen/spotify-cli-linux
Author: Piotr Wittchen
Author-email: piotr.wittchen@gmail.com
License: GPL 3.0
Classifier: Development Status :: 4 - Beta
Classifier: Intended Audience :: End Users/Desktop
Classifier: License :: OSI Approved :: GNU General Public License v3 (GPLv3)
Classifier: Operating System :: POSIX :: Linux
Classifier: Programming Language :: Python
Classifier: Topic :: Multimedia :: Sound/Audio
Requires-Python: >=3.12.7
License-File: LICENSE
